api_trello/__init__.py
api_trello/pydantic_model.py
api_trello/trello_json_client.py
python_trello_api-0.0.1.dist-info/LICENSE
python_trello_api-0.0.1.dist-info/METADATA
python_trello_api-0.0.1.dist-info/WHEEL
python_trello_api-0.0.1.dist-info/top_level.txt
python_trello_api-0.0.1.dist-info/RECORD
