Metadata-Version: 2.1
Name: python-trello-api
Version: 0.0.1
Summary: Simple and fast client to call rest-api endpoints `https://trello.com/1/` using aiohttp package
Home-page: https://github.com/DmitriyKalekin/python-trello-api
Author: Dmitriy Kalekin
Author-email: herrhorror@gmail.com
License: UNKNOWN
Project-URL: Source, https://github.com/DmitriyKalekin/python-telegram-bot-api
Keywords: pydantic trello rest api sdk client
Platform: UNKNOWN
Classifier: Intended Audience :: Developers
Classifier: Programming Language :: Python :: 3.8
Classifier: Topic :: Software Development :: Build Tools
Classifier: License :: OSI Approved :: GNU Lesser General Public License v2 or later (LGPLv2+)
Classifier: Operating System :: OS Independent
Requires-Python: >=3.7, <4
Requires-Dist: aiohttp (>=3.6.2)
Provides-Extra: test
Requires-Dist: pytest (>=6.1.2) ; extra == 'test'
Requires-Dist: pytest-asyncio (>=0.14.0) ; extra == 'test'
Requires-Dist: pytest-cov (>=2.10.1) ; extra == 'test'
Requires-Dist: pytest-xdist (>=2.1.0) ; extra == 'test'
Requires-Dist: aioresponses (>=0.7.1) ; extra == 'test'
